mcvqoe/hub/MCV-logo.png
mcvqoe/hub/MCV-sm.ico
mcvqoe/hub/MCV-sm.png
mcvqoe/hub/TestEquipment.csv
mcvqoe/hub/__init__.py
mcvqoe/hub/__main__.py
mcvqoe/hub/accesstime_gui.py
mcvqoe/hub/common.py
mcvqoe/hub/dev_dly_char_example.png
mcvqoe/hub/eval_access.py
mcvqoe/hub/eval_app.py
mcvqoe/hub/eval_diagnostics.py
mcvqoe/hub/eval_index.py
mcvqoe/hub/eval_intell.py
mcvqoe/hub/eval_m2e.py
mcvqoe/hub/eval_measurement_select.py
mcvqoe/hub/eval_psud.py
mcvqoe/hub/eval_shared.py
mcvqoe/hub/eval_tvo.py
mcvqoe/hub/intelligibility_gui.py
mcvqoe/hub/loadandsave.py
mcvqoe/hub/m2e_gui.py
mcvqoe/hub/mcv_qoe_gui.py
mcvqoe/hub/menu_icon.png
mcvqoe/hub/pscr_logo.png
mcvqoe/hub/psud_gui.py
mcvqoe/hub/shared.py
mcvqoe/hub/tk_threading.py
mcvqoe/hub/tvo_gui.py
mcvqoe/hub/version.py
mcvqoe-1.2.3.dist-info/LICENSE.md
mcvqoe-1.2.3.dist-info/METADATA
mcvqoe-1.2.3.dist-info/WHEEL
mcvqoe-1.2.3.dist-info/entry_points.txt
mcvqoe-1.2.3.dist-info/top_level.txt
mcvqoe-1.2.3.dist-info/RECORD
