Metadata-Version: 2.2
Name: mcvqoe
Version: 1.2.3
Summary: Graphical interface for mcvqoe measurements
Home-page: https://github.com/usnistgov/mcvqoe
Author: PSCR
Author-email: PSCR@PSCR.gov
License: NIST software License
Classifier: Programming Language :: Python :: 3
Classifier: License :: Public Domain
Classifier: Operating System :: OS Independent
Requires-Python: >=3.8
License-File: LICENSE.md
Requires-Dist: abcmrt16
Requires-Dist: mcvqoe-base
Requires-Dist: mcvqoe-psud
Requires-Dist: mcvqoe-intelligibility
Requires-Dist: mcvqoe-accesstime
Requires-Dist: mcvqoe-mouth2ear
Requires-Dist: mcvqoe-tvo
Requires-Dist: numpy
Requires-Dist: pandas
Requires-Dist: dash
Requires-Dist: flask
Requires-Dist: plotly
Requires-Dist: requests
Requires-Dist: pillow
Requires-Dist: scipy
Requires-Dist: werkzeug<2.1
Dynamic: author
Dynamic: author-email
Dynamic: classifier
Dynamic: description
Dynamic: description-content-type
Dynamic: home-page
Dynamic: license
Dynamic: requires-dist
Dynamic: requires-python
Dynamic: summary
